{
  "method": "edu.handong.csee.isel.machinelearning.DNN_node.get_w(I)F",
  "map": [
    {
      "asm_id": 0,
      "tok_id": 0,
      "byte_index": 0,
      "size": 1,
      "hex": "2A"
    },
    {
      "asm_id": 1,
      "tok_id": 1,
      "byte_index": 1,
      "size": 3,
      "hex": "B40020"
    },
    {
      "asm_id": 2,
      "tok_id": 2,
      "byte_index": 4,
      "size": 1,
      "hex": "1B"
    },
    {
      "asm_id": 3,
      "tok_id": 3,
      "byte_index": 5,
      "size": 1,
      "hex": "32"
    },
    {
      "asm_id": 4,
      "tok_id": 4,
      "byte_index": 6,
      "size": 1,
      "hex": "03"
    },
    {
      "asm_id": 5,
      "tok_id": 5,
      "byte_index": 7,
      "size": 1,
      "hex": "30"
    },
    {
      "asm_id": 6,
      "tok_id": 6,
      "byte_index": 8,
      "size": 1,
      "hex": "AE00000002"
    }
  ],
  "method_code_size": 9,
  "align_score": 14,
  "missing_count": 0,
  "btok_method_index": 3
}